{"nodes": [{"id": "c_users_financefaculty_desktop_refinitiv_project_main_findata_findata_ingestion_ingest_py", "label": "ingest.py", "file_type": "code", "source_file": "ingestion/ingest.py", "source_location": "L1"}, {"id": "ingestion_ingest_setup_db", "label": "setup_db()", "file_type": "code", "source_file": "ingestion/ingest.py", "source_location": "L61"}, {"id": "str", "label": "str", "file_type": "code", "source_file": "ingestion/ingest.py", "source_location": "L61"}, {"id": "duckdbpyconnection", "label": "DuckDBPyConnection", "file_type": "code", "source_file": "ingestion/ingest.py", "source_location": "L61"}, {"id": "ingestion_ingest_seed_aliases", "label": "seed_aliases()", "file_type": "code", "source_file": "ingestion/ingest.py", "source_location": "L67"}, {"id": "ingestion_ingest_ingest_file", "label": "ingest_file()", "file_type": "code", "source_file": "ingestion/ingest.py", "source_location": "L75"}, {"id": "ingestion_ingest_ingest_folder", "label": "ingest_folder()", "file_type": "code", "source_file": "ingestion/ingest.py", "source_location": "L110"}, {"id": "ingestion_ingest_rationale_1", "label": "ingestion/ingest.py  Ingests all CF Export .xlsx files from a folder into a Duck", "file_type": "rationale", "source_file": "ingestion/ingest.py", "source_location": "L1"}], "edges": [{"source": "c_users_financefaculty_desktop_refinitiv_project_main_findata_findata_ingestion_ingest_py", "target": "os", "relation": "imports", "context": "import", "confidence": "EXTRACTED", "source_file": "ingestion/ingest.py", "source_location": "L13", "weight": 1.0}, {"source": "c_users_financefaculty_desktop_refinitiv_project_main_findata_findata_ingestion_ingest_py", "target": "sys", "relation": "imports", "context": "import", "confidence": "EXTRACTED", "source_file": "ingestion/ingest.py", "source_location": "L14", "weight": 1.0}, {"source": "c_users_financefaculty_desktop_refinitiv_project_main_findata_findata_ingestion_ingest_py", "target": "argparse", "relation": "imports", "context": "import", "confidence": "EXTRACTED", "source_file": "ingestion/ingest.py", "source_location": "L15", "weight": 1.0}, {"source": "c_users_financefaculty_desktop_refinitiv_project_main_findata_findata_ingestion_ingest_py", "target": "logging", "relation": "imports", "context": "import", "confidence": "EXTRACTED", "source_file": "ingestion/ingest.py", "source_location": "L16", "weight": 1.0}, {"source": "c_users_financefaculty_desktop_refinitiv_project_main_findata_findata_ingestion_ingest_py", "target": "duckdb", "relation": "imports", "context": "import", "confidence": "EXTRACTED", "source_file": "ingestion/ingest.py", "source_location": "L17", "weight": 1.0}, {"source": "c_users_financefaculty_desktop_refinitiv_project_main_findata_findata_ingestion_ingest_py", "target": "pandas", "relation": "imports", "context": "import", "confidence": "EXTRACTED", "source_file": "ingestion/ingest.py", "source_location": "L18", "weight": 1.0}, {"source": "c_users_financefaculty_desktop_refinitiv_project_main_findata_findata_ingestion_ingest_py", "target": "pathlib", "relation": "imports_from", "context": "import", "confidence": "EXTRACTED", "source_file": "ingestion/ingest.py", "source_location": "L19", "weight": 1.0}, {"source": "c_users_financefaculty_desktop_refinitiv_project_main_findata_findata_ingestion_ingest_py", "target": "ingestion_parser", "relation": "imports_from", "context": "import", "confidence": "EXTRACTED", "source_file": "ingestion/ingest.py", "source_location": "L23", "weight": 1.0}, {"source": "c_users_financefaculty_desktop_refinitiv_project_main_findata_findata_ingestion_ingest_py", "target": "ingestion_aliases", "relation": "imports_from", "context": "import", "confidence": "EXTRACTED", "source_file": "ingestion/ingest.py", "source_location": "L24", "weight": 1.0}, {"source": "c_users_financefaculty_desktop_refinitiv_project_main_findata_findata_ingestion_ingest_py", "target": "ingestion_ingest_setup_db", "relation": "contains", "confidence": "EXTRACTED", "source_file": "ingestion/ingest.py", "source_location": "L61", "weight": 1.0}, {"source": "ingestion_ingest_setup_db", "target": "str", "relation": "references", "context": "parameter_type", "confidence": "EXTRACTED", "source_file": "ingestion/ingest.py", "source_location": "L61", "weight": 1.0}, {"source": "ingestion_ingest_setup_db", "target": "duckdbpyconnection", "relation": "references", "context": "return_type", "confidence": "EXTRACTED", "source_file": "ingestion/ingest.py", "source_location": "L61", "weight": 1.0}, {"source": "c_users_financefaculty_desktop_refinitiv_project_main_findata_findata_ingestion_ingest_py", "target": "ingestion_ingest_seed_aliases", "relation": "contains", "confidence": "EXTRACTED", "source_file": "ingestion/ingest.py", "source_location": "L67", "weight": 1.0}, {"source": "ingestion_ingest_seed_aliases", "target": "duckdbpyconnection", "relation": "references", "context": "parameter_type", "confidence": "EXTRACTED", "source_file": "ingestion/ingest.py", "source_location": "L67", "weight": 1.0}, {"source": "c_users_financefaculty_desktop_refinitiv_project_main_findata_findata_ingestion_ingest_py", "target": "ingestion_ingest_ingest_file", "relation": "contains", "confidence": "EXTRACTED", "source_file": "ingestion/ingest.py", "source_location": "L75", "weight": 1.0}, {"source": "ingestion_ingest_ingest_file", "target": "duckdbpyconnection", "relation": "references", "context": "parameter_type", "confidence": "EXTRACTED", "source_file": "ingestion/ingest.py", "source_location": "L75", "weight": 1.0}, {"source": "ingestion_ingest_ingest_file", "target": "str", "relation": "references", "context": "parameter_type", "confidence": "EXTRACTED", "source_file": "ingestion/ingest.py", "source_location": "L75", "weight": 1.0}, {"source": "c_users_financefaculty_desktop_refinitiv_project_main_findata_findata_ingestion_ingest_py", "target": "ingestion_ingest_ingest_folder", "relation": "contains", "confidence": "EXTRACTED", "source_file": "ingestion/ingest.py", "source_location": "L110", "weight": 1.0}, {"source": "ingestion_ingest_ingest_folder", "target": "str", "relation": "references", "context": "parameter_type", "confidence": "EXTRACTED", "source_file": "ingestion/ingest.py", "source_location": "L110", "weight": 1.0}, {"source": "ingestion_ingest_ingest_folder", "target": "str", "relation": "references", "context": "parameter_type", "confidence": "EXTRACTED", "source_file": "ingestion/ingest.py", "source_location": "L110", "weight": 1.0}, {"source": "ingestion_ingest_ingest_folder", "target": "ingestion_ingest_setup_db", "relation": "calls", "context": "call", "confidence": "EXTRACTED", "source_file": "ingestion/ingest.py", "source_location": "L117", "weight": 1.0}, {"source": "ingestion_ingest_ingest_folder", "target": "ingestion_ingest_seed_aliases", "relation": "calls", "context": "call", "confidence": "EXTRACTED", "source_file": "ingestion/ingest.py", "source_location": "L118", "weight": 1.0}, {"source": "ingestion_ingest_ingest_folder", "target": "ingestion_ingest_ingest_file", "relation": "calls", "context": "call", "confidence": "EXTRACTED", "source_file": "ingestion/ingest.py", "source_location": "L122", "weight": 1.0}, {"source": "ingestion_ingest_rationale_1", "target": "c_users_financefaculty_desktop_refinitiv_project_main_findata_findata_ingestion_ingest_py", "relation": "rationale_for", "confidence": "EXTRACTED", "source_file": "ingestion/ingest.py", "source_location": "L1", "weight": 1.0}], "raw_calls": [{"caller_nid": "ingestion_ingest_setup_db", "callee": "connect", "is_member_call": true, "source_file": "C:\\Users\\Financefaculty\\Desktop\\Refinitiv-Project-main\\findata\\findata\\ingestion\\ingest.py", "source_location": "L62"}, {"caller_nid": "ingestion_ingest_setup_db", "callee": "execute", "is_member_call": true, "source_file": "C:\\Users\\Financefaculty\\Desktop\\Refinitiv-Project-main\\findata\\findata\\ingestion\\ingest.py", "source_location": "L63"}, {"caller_nid": "ingestion_ingest_seed_aliases", "callee": "fetchall", "is_member_call": true, "source_file": "C:\\Users\\Financefaculty\\Desktop\\Refinitiv-Project-main\\findata\\findata\\ingestion\\ingest.py", "source_location": "L68"}, {"caller_nid": "ingestion_ingest_seed_aliases", "callee": "execute", "is_member_call": true, "source_file": "C:\\Users\\Financefaculty\\Desktop\\Refinitiv-Project-main\\findata\\findata\\ingestion\\ingest.py", "source_location": "L68"}, {"caller_nid": "ingestion_ingest_seed_aliases", "callee": "upper", "is_member_call": true, "source_file": "C:\\Users\\Financefaculty\\Desktop\\Refinitiv-Project-main\\findata\\findata\\ingestion\\ingest.py", "source_location": "L69"}, {"caller_nid": "ingestion_ingest_seed_aliases", "callee": "items", "is_member_call": true, "source_file": "C:\\Users\\Financefaculty\\Desktop\\Refinitiv-Project-main\\findata\\findata\\ingestion\\ingest.py", "source_location": "L69"}, {"caller_nid": "ingestion_ingest_seed_aliases", "callee": "upper", "is_member_call": true, "source_file": "C:\\Users\\Financefaculty\\Desktop\\Refinitiv-Project-main\\findata\\findata\\ingestion\\ingest.py", "source_location": "L69"}, {"caller_nid": "ingestion_ingest_seed_aliases", "callee": "executemany", "is_member_call": true, "source_file": "C:\\Users\\Financefaculty\\Desktop\\Refinitiv-Project-main\\findata\\findata\\ingestion\\ingest.py", "source_location": "L71"}, {"caller_nid": "ingestion_ingest_seed_aliases", "callee": "info", "is_member_call": true, "source_file": "C:\\Users\\Financefaculty\\Desktop\\Refinitiv-Project-main\\findata\\findata\\ingestion\\ingest.py", "source_location": "L72"}, {"caller_nid": "ingestion_ingest_ingest_file", "callee": "fetchone", "is_member_call": true, "source_file": "C:\\Users\\Financefaculty\\Desktop\\Refinitiv-Project-main\\findata\\findata\\ingestion\\ingest.py", "source_location": "L76"}, {"caller_nid": "ingestion_ingest_ingest_file", "callee": "execute", "is_member_call": true, "source_file": "C:\\Users\\Financefaculty\\Desktop\\Refinitiv-Project-main\\findata\\findata\\ingestion\\ingest.py", "source_location": "L76"}, {"caller_nid": "ingestion_ingest_ingest_file", "callee": "debug", "is_member_call": true, "source_file": "C:\\Users\\Financefaculty\\Desktop\\Refinitiv-Project-main\\findata\\findata\\ingestion\\ingest.py", "source_location": "L80"}, {"caller_nid": "ingestion_ingest_ingest_file", "callee": "info", "is_member_call": true, "source_file": "C:\\Users\\Financefaculty\\Desktop\\Refinitiv-Project-main\\findata\\findata\\ingestion\\ingest.py", "source_location": "L83"}, {"caller_nid": "ingestion_ingest_ingest_file", "callee": "parse_file", "is_member_call": false, "source_file": "C:\\Users\\Financefaculty\\Desktop\\Refinitiv-Project-main\\findata\\findata\\ingestion\\ingest.py", "source_location": "L85"}, {"caller_nid": "ingestion_ingest_ingest_file", "callee": "error", "is_member_call": true, "source_file": "C:\\Users\\Financefaculty\\Desktop\\Refinitiv-Project-main\\findata\\findata\\ingestion\\ingest.py", "source_location": "L87"}, {"caller_nid": "ingestion_ingest_ingest_file", "callee": "warning", "is_member_call": true, "source_file": "C:\\Users\\Financefaculty\\Desktop\\Refinitiv-Project-main\\findata\\findata\\ingestion\\ingest.py", "source_location": "L91"}, {"caller_nid": "ingestion_ingest_ingest_file", "callee": "execute", "is_member_call": true, "source_file": "C:\\Users\\Financefaculty\\Desktop\\Refinitiv-Project-main\\findata\\findata\\ingestion\\ingest.py", "source_location": "L98"}, {"caller_nid": "ingestion_ingest_ingest_file", "callee": "execute", "is_member_call": true, "source_file": "C:\\Users\\Financefaculty\\Desktop\\Refinitiv-Project-main\\findata\\findata\\ingestion\\ingest.py", "source_location": "L100"}, {"caller_nid": "ingestion_ingest_ingest_file", "callee": "execute", "is_member_call": true, "source_file": "C:\\Users\\Financefaculty\\Desktop\\Refinitiv-Project-main\\findata\\findata\\ingestion\\ingest.py", "source_location": "L102"}, {"caller_nid": "ingestion_ingest_ingest_file", "callee": "info", "is_member_call": true, "source_file": "C:\\Users\\Financefaculty\\Desktop\\Refinitiv-Project-main\\findata\\findata\\ingestion\\ingest.py", "source_location": "L107"}, {"caller_nid": "ingestion_ingest_ingest_folder", "callee": "rglob", "is_member_call": true, "source_file": "C:\\Users\\Financefaculty\\Desktop\\Refinitiv-Project-main\\findata\\findata\\ingestion\\ingest.py", "source_location": "L111"}, {"caller_nid": "ingestion_ingest_ingest_folder", "callee": "Path", "is_member_call": false, "source_file": "C:\\Users\\Financefaculty\\Desktop\\Refinitiv-Project-main\\findata\\findata\\ingestion\\ingest.py", "source_location": "L111"}, {"caller_nid": "ingestion_ingest_ingest_folder", "callee": "warning", "is_member_call": true, "source_file": "C:\\Users\\Financefaculty\\Desktop\\Refinitiv-Project-main\\findata\\findata\\ingestion\\ingest.py", "source_location": "L113"}, {"caller_nid": "ingestion_ingest_ingest_folder", "callee": "info", "is_member_call": true, "source_file": "C:\\Users\\Financefaculty\\Desktop\\Refinitiv-Project-main\\findata\\findata\\ingestion\\ingest.py", "source_location": "L116"}, {"caller_nid": "ingestion_ingest_ingest_folder", "callee": "info", "is_member_call": true, "source_file": "C:\\Users\\Financefaculty\\Desktop\\Refinitiv-Project-main\\findata\\findata\\ingestion\\ingest.py", "source_location": "L121"}, {"caller_nid": "ingestion_ingest_ingest_folder", "callee": "close", "is_member_call": true, "source_file": "C:\\Users\\Financefaculty\\Desktop\\Refinitiv-Project-main\\findata\\findata\\ingestion\\ingest.py", "source_location": "L124"}, {"caller_nid": "ingestion_ingest_ingest_folder", "callee": "info", "is_member_call": true, "source_file": "C:\\Users\\Financefaculty\\Desktop\\Refinitiv-Project-main\\findata\\findata\\ingestion\\ingest.py", "source_location": "L125"}]}